{
    "1": 451,
    "2": 720,
    "5": 5506,
    "7": 487,
    "8": 158,
    "9": 3172,
    "11": 2955,
    "12": 548,
    "14": 1829,
    "10": 894,
    "16": 118,
    "19": 2447,
    "21": 493,
    "23": 1852,
    "18": 844,
    "6": 132,
    "24": 638,
    "26": 136,
    "29": 1662,
    "31": 3130,
    "22": 487,
    "32": 976,
    "4": 1168,
    "34": 1810,
    "36": 649,
    "33": 1384,
    "38": 22,
    "41": 485,
    "42": 931,
    "45": 3186,
    "47": 479,
    "35": 2090,
    "46": 129,
    "20": 146,
    "28": 702,
    "48": 1030,
    "3": 2375,
    "44": 674,
    "17": 502,
    "51": 700,
    "37": 3137,
    "53": 1459,
    "40": 141,
    "55": 256,
    "25": 1690,
    "43": 2365,
    "27": 482,
    "15": 1833,
    "57": 1691,
    "59": 4841,
    "61": 2273,
    "52": 633,
    "13": 1510,
    "56": 673,
    "49": 2286,
    "63": 8,
    "64": 240,
    "66": 3,
    "0": 164,
    "58": 687,
    "69": 8,
    "30": 201,
    "39": 352,
    "71": 493,
    "65": 393,
    "73": 153,
    "75": 819,
    "77": 924,
    "79": 1069,
    "50": 152,
    "81": 713,
    "83": 550,
    "85": 156,
    "74": 204,
    "80": 338,
    "76": 61,
    "78": 113,
    "54": 43,
    "60": 132,
    "86": 87,
    "87": 199,
    "89": 19,
    "72": 24,
    "90": 18,
    "91": 61,
    "92": 1,
    "67": 7,
    "93": 3,
    "82": 41,
    "70": 134,
    "84": 13,
    "62": 2,
    "68": 2
}